UFOpticSim/__init__.py
UFOpticSim/beamsplitter.py
UFOpticSim/calc.py
UFOpticSim/grating.py
UFOpticSim/laser.py
UFOpticSim/lens.py
UFOpticSim/material.py
UFOpticSim/mirror.py
UFOpticSim/prism.py
UFOpticSim/pulseprofile.py
UFOpticSim/results.py
UFOpticSim/screen.py
UFOpticSim/simulation.py
UFOpticSim-0.1.dist-info/METADATA
UFOpticSim-0.1.dist-info/WHEEL
UFOpticSim-0.1.dist-info/top_level.txt
UFOpticSim-0.1.dist-info/RECORD
