Metadata-Version: 2.1
Name: UFOpticSim
Version: 0.1
Summary: Ultra Fast Optics Simulations with Python3
Author: Anirudh Yamunan Govindarajan
Author-email: yamunan.bitset@gmail.com
License: MIT
Project-URL: Source Repository, https://github.com/yamunan-bitset/UFOpticSim/
Requires-Dist: numpy
Requires-Dist: pygame
